latex_wc/__init__.py
latex_wc/cli.py
latex_wc/counting.py
latex_wc/io_utils.py
latex_wc/latex_tokens.py
latex_wc/models.py
latex_wc/writers.py
latex_wc-0.1.0.dist-info/licenses/LICENSE
latex_wc-0.1.0.dist-info/METADATA
latex_wc-0.1.0.dist-info/WHEEL
latex_wc-0.1.0.dist-info/entry_points.txt
latex_wc-0.1.0.dist-info/top_level.txt
latex_wc-0.1.0.dist-info/RECORD
