Metadata-Version: 2.4
Name: latex-wc
Version: 0.1.0
Summary: Count words in LaTeX documents while ignoring commands, math, and common non-text regions.
Author: Seth Barrett
License-Expression: Unlicense
Project-URL: Repository, https://github.com/sethbarrett50/LaTeX-wc
Project-URL: Issues, https://github.com/sethbarrett50/LaTeX-wc/issues
Keywords: latex,word-count,tex,cli
Classifier: Programming Language :: Python :: 3
Classifier: Programming Language :: Python :: 3 :: Only
Classifier: Programming Language :: Python :: 3.11
Classifier: Programming Language :: Python :: 3.12
Classifier: Programming Language :: Python :: 3.13
Classifier: Environment :: Console
Classifier: Intended Audience :: Science/Research
Classifier: Topic :: Text Processing
Requires-Python: >=3.11
License-File: LICENSE
Dynamic: license-file
